devnix/__init__.py
devnix/checker.py
devnix/cleaner.py
devnix/cli.py
devnix/detector.py
devnix/doctor.py
devnix/envsync.py
devnix/runners.py
devnix/utils.py
devnix-0.1.0.dist-info/licenses/LICENSE
devnix-0.1.0.dist-info/METADATA
devnix-0.1.0.dist-info/WHEEL
devnix-0.1.0.dist-info/entry_points.txt
devnix-0.1.0.dist-info/top_level.txt
devnix-0.1.0.dist-info/RECORD
