Metadata-Version: 2.4
Name: devnix
Version: 0.1.0
Summary: Safe, opinionated Python project workflows
Author: Samyog Maharjan
License: MIT
Project-URL: Homepage, https://github.com/Iam-samyog/devnix
Project-URL: Repository, https://github.com/Iam-samyog/devnix
Requires-Python: >=3.9
License-File: LICENSE
Requires-Dist: typer>=0.9.0
Requires-Dist: rich>=13.0.0
Requires-Dist: python-dotenv>=1.0.0
Dynamic: license-file
